hackattack_awa_matrix/__init__.py
hackattack_awa_matrix/__main__.py
hackattack_awa_matrix/auth.py
hackattack_awa_matrix/awarenessmeasures.py
hackattack_awa_matrix/command_line.py
hackattack_awa_matrix/countermeasures.py
hackattack_awa_matrix/db.py
hackattack_awa_matrix/employee.py
hackattack_awa_matrix/project.py
hackattack_awa_matrix/schema.sql
hackattack_awa_matrix/threat.py
hackattack_awa_matrix/static/css/bootstrap.min.css
hackattack_awa_matrix/static/css/fontawesome.min.css
hackattack_awa_matrix/static/css/style.css
hackattack_awa_matrix/static/img/hackattack_pdf.jpg
hackattack_awa_matrix/static/img/hackattack_white.png
hackattack_awa_matrix/static/js/Chart.min.js
hackattack_awa_matrix/static/js/Sortable.min.js
hackattack_awa_matrix/static/js/bootstrap.min.js
hackattack_awa_matrix/static/js/jquery-3.5.1.min.js
hackattack_awa_matrix/static/js/popper.min.js
hackattack_awa_matrix/static/webfonts/fa-brands-400.eot
hackattack_awa_matrix/static/webfonts/fa-brands-400.svg
hackattack_awa_matrix/static/webfonts/fa-brands-400.ttf
hackattack_awa_matrix/static/webfonts/fa-brands-400.woff
hackattack_awa_matrix/static/webfonts/fa-brands-400.woff2
hackattack_awa_matrix/static/webfonts/fa-regular-400.eot
hackattack_awa_matrix/static/webfonts/fa-regular-400.svg
hackattack_awa_matrix/static/webfonts/fa-regular-400.ttf
hackattack_awa_matrix/static/webfonts/fa-regular-400.woff
hackattack_awa_matrix/static/webfonts/fa-regular-400.woff2
hackattack_awa_matrix/static/webfonts/fa-solid-900.eot
hackattack_awa_matrix/static/webfonts/fa-solid-900.svg
hackattack_awa_matrix/static/webfonts/fa-solid-900.ttf
hackattack_awa_matrix/static/webfonts/fa-solid-900.woff
hackattack_awa_matrix/static/webfonts/fa-solid-900.woff2
hackattack_awa_matrix/templates/base.html
hackattack_awa_matrix/templates/index.html
hackattack_awa_matrix/templates/license.html
hackattack_awa_matrix/templates/auth/change_pw.html
hackattack_awa_matrix/templates/auth/index.html
hackattack_awa_matrix/templates/auth/login.html
hackattack_awareness_matrix-0.7.6.dist-info/METADATA
hackattack_awareness_matrix-0.7.6.dist-info/WHEEL
hackattack_awareness_matrix-0.7.6.dist-info/entry_points.txt
hackattack_awareness_matrix-0.7.6.dist-info/top_level.txt
hackattack_awareness_matrix-0.7.6.dist-info/RECORD
