Metadata-Version: 2.1
Name: hackattack-awareness-matrix
Version: 0.7.6
Summary: A packaged web-application that should support users when dealing with awareness-measures in their companies
Home-page: https://www.hackattack.com/awareness/
Author: Daniel Sternig - HACKATTACK IT Security GmbH
Author-email: daniel.sternig@hackattack.com
License: UNKNOWN
Platform: UNKNOWN
Classifier: Programming Language :: Python :: 3
Classifier: Operating System :: OS Independent
Requires-Python: >=3.6
Requires-Dist: python-dateutil
Requires-Dist: flask
Requires-Dist: gevent
Requires-Dist: XlsxWriter
